opengenes_mcp/__init__.py
opengenes_mcp/server.py
opengenes_mcp-0.2.0.dist-info/METADATA
opengenes_mcp-0.2.0.dist-info/WHEEL
opengenes_mcp-0.2.0.dist-info/entry_points.txt
opengenes_mcp-0.2.0.dist-info/licenses/LICENSE
opengenes_mcp-0.2.0.dist-info/RECORD
