Metadata-Version: 2.4
Name: opengenes-mcp
Version: 0.2.0
Summary: MCP for OpenGenes
Author-email: antonkulaga <antonkulaga@gmail.com>, Livia Zaharia <liviazaharia2020@gmail.com>
License-File: LICENSE
Requires-Python: >=3.10
Requires-Dist: aiosqlite>=0.20.0
Requires-Dist: eliot>=1.17.5
Requires-Dist: fastmcp>=2.9.1
Requires-Dist: huggingface-hub>=0.33.1
Requires-Dist: pycomfort>=0.0.18
Requires-Dist: sqlite-utils>=3.38
Requires-Dist: typer>=0.16.0
